apex_legends_voicelines/__init__.py
apex_legends_voicelines/__main__.py
apex_legends_voicelines/assets/__init__.py
apex_legends_voicelines/assets/voicelines.json
apex_legends_voicelines-1.0.0.dist-info/entry_points.txt
apex_legends_voicelines-1.0.0.dist-info/LICENSE.txt
apex_legends_voicelines-1.0.0.dist-info/WHEEL
apex_legends_voicelines-1.0.0.dist-info/METADATA
apex_legends_voicelines-1.0.0.dist-info/RECORD
