Metadata-Version: 2.1
Name: apex-legends-voicelines
Version: 1.0.0
Summary: Python program to get a random voiceline from an Apex Legend
Home-page: https://justine.kizhak.com/projects/apex-legends-voicelines
License: MIT
Keywords: entertainment,Apex Legends,game
Author: Justine Kizhakkinedath
Author-email: justine@kizhak.com
Requires-Python: >=3.8,<4.0
Classifier: Development Status :: 5 - Production/Stable
Classifier: Intended Audience :: End Users/Desktop
Classifier: License :: OSI Approved :: MIT License
Classifier: Operating System :: OS Independent
Classifier: Programming Language :: Python :: 3
Classifier: Programming Language :: Python :: 3.8
Classifier: Topic :: Games/Entertainment
Classifier: Topic :: Text Editors :: Emacs
Project-URL: Bug Reports, https://gitlab.com/justinekizhak/apex-legends-voicelines/issues
Project-URL: Repository, https://gitlab.com/justinekizhak/apex-legends-voicelines
Project-URL: Say Thanks!, https://saythanks.io/to/justine%40kizhak.com
